copilot/__init__.py
django_copilot-0.1.0.dist-info/WHEEL
django_copilot-0.1.0.dist-info/METADATA
django_copilot-0.1.0.dist-info/RECORD
