Metadata-Version: 2.1
Name: django-copilot
Version: 0.1.0
Summary: Django copilot
Home-page: https://github.com/vitalik/django-copilot
Author: Vitaliy Kucheryaviy
Author-email: ppr.vitaly@gmail.com
